{"skeleton":{"hash":"QA90CkfjjCQ","spine":"4.0.36","x":-17.65,"y":-4.58,"width":36.05,"height":13.29,"images":"../../../textures/GAME/","audio":""},"bones":[{"name":"root","scaleX":0.35,"scaleY":0.35},{"name":"center-bone","parent":"root","x":3.57,"y":4.54},{"name":"fire-bone","parent":"root","length":27.96,"x":-24.94,"y":14.03,"scaleX":2.85,"scaleY":2.85},{"name":"fire-secondary-bone","parent":"root","length":13.41,"x":20.66,"y":2.03,"scaleX":2.85,"scaleY":2.85},{"name":"hook-bone","parent":"root","length":5.46,"x":-16.1,"y":20.41,"scaleX":2.5,"scaleY":2.5},{"name":"laser-bone","parent":"root","length":3.3,"x":30.93,"y":7.26,"scaleX":2.5,"scaleY":2.5},{"name":"shell-bone","parent":"root","length":3.75,"rotation":90,"x":-19.66,"y":2.01,"scaleX":2.5,"scaleY":2.5}],"slots":[{"name":"clip","bone":"root","attachment":"default"},{"name":"body","bone":"root","attachment":"body"},{"name":"scope","bone":"root","attachment":"default"},{"name":"holder","bone":"root"}],"skins":[{"name":"weapon-default","attachments":{"body":{"body":{"name":"auga3-skin","x":1.06,"y":7.43,"width":103,"height":27}},"clip":{"default":{"name":"aug-clip-default","x":-21.41,"y":-4.08,"width":14,"height":18}},"holder":{"m203":{"name":"auga3-gl-m203","x":36.58,"y":3.42,"width":46,"height":15},"on":{"name":"auga3-holder","x":37.09,"y":2.9,"width":21,"height":16}},"scope":{"default":{"name":"auga3-scope-default","x":14.63,"y":22.39,"width":56,"height":5},"truglo":{"name":"fn2000-scope-truglo","x":-0.4,"y":23.93,"width":14,"height":10},"acog":{"name":"sig552-scope-acog","x":-0.45,"y":24.33,"width":20,"height":11}}}},{"name":"weapon-demigod","attachments":{"body":{"body":{"name":"auga3-skin-demigod","x":1.06,"y":7.43,"width":103,"height":27}},"clip":{"default":{"name":"aug-clip-default-demigod","x":-21.41,"y":-4.08,"width":14,"height":18}},"holder":{"m203":{"name":"auga3-gl-m203","x":36.58,"y":3.42,"width":46,"height":15},"on":{"name":"auga3-holder","x":37.09,"y":2.9,"width":21,"height":16}},"scope":{"default":{"name":"auga3-scope-default","x":14.63,"y":22.39,"width":56,"height":5},"truglo":{"name":"fn2000-scope-truglo","x":-0.4,"y":23.93,"width":14,"height":10},"acog":{"name":"sig552-scope-acog","x":-0.45,"y":24.33,"width":20,"height":11}}}},{"name":"weapon-gift","attachments":{"body":{"body":{"name":"auga3-skin-gift","x":1.06,"y":7.43,"width":103,"height":27}},"clip":{"default":{"name":"aug-clip-default-gift","x":-21.41,"y":-4.08,"width":14,"height":18}},"holder":{"m203":{"name":"auga3-gl-m203","x":36.58,"y":3.42,"width":46,"height":15},"on":{"name":"auga3-holder","x":37.09,"y":2.9,"width":21,"height":16}},"scope":{"default":{"name":"auga3-scope-default","x":14.63,"y":22.39,"width":56,"height":5},"truglo":{"name":"fn2000-scope-truglo","x":-0.4,"y":23.93,"width":14,"height":10},"acog":{"name":"sig552-scope-acog","x":-0.45,"y":24.33,"width":20,"height":11}}}},{"name":"weapon-icecream","attachments":{"body":{"body":{"name":"auga3-skin-icecream","x":1.06,"y":7.43,"width":103,"height":27}},"clip":{"default":{"name":"aug-clip-default-icecream","x":-21.41,"y":-4.08,"width":14,"height":18}},"holder":{"m203":{"name":"auga3-gl-m203-icecream","x":36.58,"y":3.42,"width":46,"height":15},"on":{"name":"auga3-holder-icecream","x":37.09,"y":2.9,"width":21,"height":16}},"scope":{"default":{"name":"auga3-scope-default-icecream","x":14.63,"y":22.39,"width":56,"height":5},"truglo":{"name":"fn2000-scope-truglo-icecream","x":-0.4,"y":23.93,"width":14,"height":10},"acog":{"name":"sig552-scope-acog-icecream","x":-0.45,"y":24.33,"width":20,"height":11}}}},{"name":"weapon-octopus","attachments":{"body":{"body":{"name":"auga3-skin-octopus","x":1.06,"y":7.43,"width":103,"height":27}},"clip":{"default":{"name":"aug-clip-default-octopus","x":-21.41,"y":-4.08,"width":14,"height":18}},"holder":{"m203":{"name":"auga3-gl-m203-octopus","x":36.58,"y":3.42,"width":46,"height":15},"on":{"name":"auga3-holder-octopus","x":37.09,"y":2.9,"width":21,"height":16}},"scope":{"default":{"name":"auga3-scope-default","x":14.63,"y":22.39,"width":56,"height":5},"truglo":{"name":"fn2000-scope-truglo-octopus","x":-0.4,"y":23.93,"width":14,"height":10},"acog":{"name":"sig552-scope-acog-octopus","x":-0.45,"y":24.33,"width":20,"height":11}}}},{"name":"weapon-outrun","attachments":{"body":{"body":{"name":"auga3-skin-outrun","x":1.06,"y":7.43,"width":103,"height":27}},"clip":{"default":{"name":"aug-clip-default-outrun","x":-21.41,"y":-4.08,"width":14,"height":18}},"holder":{"m203":{"name":"auga3-gl-m203-outrun","x":36.58,"y":3.42,"width":46,"height":15},"on":{"name":"auga3-holder-outrun","x":37.09,"y":2.9,"width":21,"height":16}},"scope":{"default":{"name":"auga3-scope-default","x":14.63,"y":22.39,"width":56,"height":5},"truglo":{"name":"fn2000-scope-truglo","x":-0.4,"y":23.93,"width":14,"height":10},"acog":{"name":"sig552-scope-acog-outrun","x":-0.45,"y":24.33,"width":20,"height":11}}}},{"name":"weapon-tokyo","attachments":{"body":{"body":{"name":"auga3-skin-tokyo","x":1.06,"y":7.43,"width":103,"height":27}},"clip":{"default":{"name":"aug-clip-default-tokyo","x":-21.41,"y":-4.08,"width":14,"height":18}},"holder":{"m203":{"name":"auga3-gl-m203","x":36.58,"y":3.42,"width":46,"height":15},"on":{"name":"auga3-holder","x":37.09,"y":2.9,"width":21,"height":16}},"scope":{"default":{"name":"auga3-scope-default","x":14.63,"y":22.39,"width":56,"height":5},"truglo":{"name":"fn2000-scope-truglo","x":-0.4,"y":23.93,"width":14,"height":10},"acog":{"name":"sig552-scope-acog","x":-0.45,"y":24.33,"width":20,"height":11}}}}],"animations":{"animation":{}}}