{"skeleton":{"hash":"MphqQPQNeDo","spine":"4.0.36","x":-17.2,"y":-5.4,"width":44.4,"height":16.4,"images":"../../../textures/GAME/","audio":""},"bones":[{"name":"root","scaleX":0.4,"scaleY":0.4},{"name":"center-bone","parent":"root","x":24.75,"y":11.21},{"name":"fire-bone","parent":"root","length":25.58,"x":3.69,"y":15.02,"scaleX":2.5,"scaleY":2.5},{"name":"fire-secondary-bone","parent":"root","length":16.8,"x":23.89,"y":4.86,"scaleX":2.5,"scaleY":2.5},{"name":"hook-bone","parent":"root","length":42.39,"rotation":-0.18,"x":1.14,"y":21.77},{"name":"laser-bone","parent":"root","length":3.39,"x":48.41,"y":10.46,"scaleX":3.5,"scaleY":2.5},{"name":"shell-bone","parent":"root","length":3.67,"rotation":90,"x":19.07,"y":11.83,"scaleX":2.5,"scaleY":2.5},{"name":"shell-secondary-bone","parent":"root","length":1.49,"rotation":90,"x":45.18,"y":6.47,"scaleX":2.5,"scaleY":2.5},{"name":"belt-a","parent":"root","x":-38.37,"y":12.58},{"name":"belt-b","parent":"root","x":50.78,"y":14.68}],"slots":[{"name":"clip","bone":"root","attachment":"default"},{"name":"butt","bone":"root","attachment":"default"},{"name":"body","bone":"root","attachment":"default"},{"name":"holder","bone":"root"},{"name":"scope","bone":"root"},{"name":"silencer","bone":"root"}],"skins":[{"name":"weapon-default","attachments":{"body":{"default":{"name":"scarl-skin","x":31,"y":10,"width":74,"height":35}},"butt":{"default":{"name":"scarl-butt-default","x":-24,"y":9.5,"width":38,"height":24}},"clip":{"default":{"name":"scarl-clip-default","x":21,"y":-4.5,"width":12,"height":18}},"holder":{"gl":{"name":"scarl-gl-fn40gl","x":36.5,"y":3,"width":59,"height":19},"on":{"name":"scarl-holder","x":36.5,"y":7,"width":7,"height":11}},"scope":{"acog":{"name":"scarl-scope-acog","x":17.5,"y":27,"width":25,"height":11}},"silencer":{"on":{"name":"scarl-silencer","x":77,"y":15,"width":26,"height":5}}}},{"name":"weapon-slalom","attachments":{"body":{"default":{"name":"scarl-skin-slalom","x":31,"y":10,"width":74,"height":35}},"butt":{"default":{"name":"scarl-butt-default-slalom","x":-24,"y":9.5,"width":38,"height":24}},"clip":{"default":{"name":"scarl-clip-default","x":21,"y":-4.5,"width":12,"height":18}},"holder":{"gl":{"name":"scarl-gl-fn40gl","x":36.5,"y":3,"width":59,"height":19},"on":{"name":"scarl-holder","x":36.5,"y":7,"width":7,"height":11}},"scope":{"acog":{"name":"scarl-scope-acog","x":17.5,"y":27,"width":25,"height":11}},"silencer":{"on":{"name":"scarl-silencer","x":77,"y":15,"width":26,"height":5}}}},{"name":"weapon-tundra","attachments":{"body":{"default":{"name":"scarl-skin-tundra","x":31,"y":10,"width":74,"height":35}},"butt":{"default":{"name":"scarl-butt-default-tundra","x":-24,"y":9.5,"width":38,"height":24}},"clip":{"default":{"name":"scarl-clip-default-tundra","x":21,"y":-4.5,"width":12,"height":18}},"holder":{"gl":{"name":"scarl-gl-fn40gl-tundra","x":36.5,"y":3,"width":59,"height":19},"on":{"name":"scarl-holder-tundra","x":36.5,"y":7,"width":7,"height":11}},"scope":{"acog":{"name":"scarl-scope-acog-tundra","x":17.5,"y":27,"width":25,"height":11}},"silencer":{"on":{"name":"scarl-silencer-tundra","x":77,"y":15,"width":26,"height":5}}}}],"animations":{"animation":{}}}